anta/__init__.py
anta/_runner.py
anta/catalog.py
anta/constants.py
anta/custom_types.py
anta/decorators.py
anta/device.py
anta/logger.py
anta/models.py
anta/py.typed
anta/runner.py
anta/settings.py
anta/tools.py
anta/cli/__init__.py
anta/cli/_main.py
anta/cli/console.py
anta/cli/utils.py
anta/cli/check/__init__.py
anta/cli/check/commands.py
anta/cli/debug/__init__.py
anta/cli/debug/commands.py
anta/cli/debug/utils.py
anta/cli/exec/__init__.py
anta/cli/exec/commands.py
anta/cli/exec/utils.py
anta/cli/get/__init__.py
anta/cli/get/commands.py
anta/cli/get/utils.py
anta/cli/nrfu/__init__.py
anta/cli/nrfu/commands.py
anta/cli/nrfu/utils.py
anta/input_models/__init__.py
anta/input_models/avt.py
anta/input_models/bfd.py
anta/input_models/connectivity.py
anta/input_models/cvx.py
anta/input_models/evpn.py
anta/input_models/flow_tracking.py
anta/input_models/hardware.py
anta/input_models/interfaces.py
anta/input_models/logging.py
anta/input_models/path_selection.py
anta/input_models/security.py
anta/input_models/services.py
anta/input_models/snmp.py
anta/input_models/stun.py
anta/input_models/system.py
anta/input_models/vlan.py
anta/input_models/routing/__init__.py
anta/input_models/routing/bgp.py
anta/input_models/routing/generic.py
anta/input_models/routing/isis.py
anta/input_models/routing/ospf.py
anta/inventory/__init__.py
anta/inventory/exceptions.py
anta/inventory/models.py
anta/reporter/__init__.py
anta/reporter/csv_reporter.py
anta/reporter/md_reporter.py
anta/result_manager/__init__.py
anta/result_manager/models.py
anta/tests/__init__.py
anta/tests/aaa.py
anta/tests/avt.py
anta/tests/bfd.py
anta/tests/configuration.py
anta/tests/connectivity.py
anta/tests/cvx.py
anta/tests/evpn.py
anta/tests/field_notices.py
anta/tests/flow_tracking.py
anta/tests/greent.py
anta/tests/hardware.py
anta/tests/interfaces.py
anta/tests/lanz.py
anta/tests/logging.py
anta/tests/mlag.py
anta/tests/multicast.py
anta/tests/path_selection.py
anta/tests/profiles.py
anta/tests/ptp.py
anta-1.6.0.dist-info/licenses/LICENSE
anta-1.6.0.dist-info/METADATA
anta-1.6.0.dist-info/WHEEL
anta-1.6.0.dist-info/entry_points.txt
anta-1.6.0.dist-info/top_level.txt
anta-1.6.0.dist-info/RECORD
